{
  "indexes": [
    {
      "collectionGroup": "posts",
      "queryScope": "COLLECTION",
      "fields": [
        {
          "fieldPath": "section",
          "order": "ASCENDING"
        },
        {
          "fieldPath": "publishDate",
          "order": "DESCENDING"
        }
      ]
    },
    {
      "collectionGroup": "posts",
      "queryScope": "COLLECTION",
      "fields": [
        {
          "fieldPath": "status",
          "order": "ASCENDING"
        },
        {
          "fieldPath": "publishDate",
          "order": "DESCENDING"
        }
      ]
    },
    {
      "collectionGroup": "posts",
      "queryScope": "COLLECTION",
      "fields": [
        {
          "fieldPath": "isFeatured",
          "order": "ASCENDING"
        },
        {
          "fieldPath": "publishDate",
          "order": "DESCENDING"
        }
      ]
    },
    {
      "collectionGroup": "tools",
      "queryScope": "COLLECTION",
      "fields": [
        {
          "fieldPath": "categoryId",
          "order": "ASCENDING"
        },
        {
          "fieldPath": "name",
          "order": "ASCENDING"
        }
      ]
    },
    {
      "collectionGroup": "tools",
      "queryScope": "COLLECTION",
      "fields": [
        {
          "fieldPath": "isFeatured",
          "order": "ASCENDING"
        },
        {
          "fieldPath": "name",
          "order": "ASCENDING"
        }
      ]
    },
    {
      "collectionGroup": "subscribers",
      "queryScope": "COLLECTION",
      "fields": [
        {
          "fieldPath": "isActive",
          "order": "ASCENDING"
        },
        {
          "fieldPath": "subscribedAt",
          "order": "DESCENDING"
        }
      ]
    },
    {
      "collectionGroup": "comments",
      "queryScope": "COLLECTION",
      "fields": [
        {
          "fieldPath": "postId",
          "order": "ASCENDING"
        },
        {
          "fieldPath": "status",
          "order": "ASCENDING"
        },
        {
          "fieldPath": "createdAt",
          "order": "DESCENDING"
        }
      ]
    },
    {
      "collectionGroup": "commentModeration",
      "queryScope": "COLLECTION",
      "fields": [
        {
          "fieldPath": "guestIpHash",
          "order": "ASCENDING"
        },
        {
          "fieldPath": "createdAt",
          "order": "DESCENDING"
        }
      ]
    }
  ],
  "fieldOverrides": []
}
